geoextent/__init__.py
geoextent/__main__.py
geoextent/lib/__init__.py
geoextent/lib/extent.py
geoextent/lib/handleCSV.py
geoextent/lib/handleRaster.py
geoextent/lib/handleVector.py
geoextent/lib/helpfunctions.py
geoextent/lib/content_providers/Zenodo.py
geoextent/lib/content_providers/__init__.py
geoextent/lib/content_providers/providers.py
geoextent-0.7.1.dist-info/AUTHORS
geoextent-0.7.1.dist-info/LICENSE
geoextent-0.7.1.dist-info/METADATA
geoextent-0.7.1.dist-info/WHEEL
geoextent-0.7.1.dist-info/entry_points.txt
geoextent-0.7.1.dist-info/top_level.txt
geoextent-0.7.1.dist-info/RECORD
