Metadata-Version: 2.1
Name: geoextent
Version: 0.7.1
Summary: A package to extract geospatial extent from files and directories
Home-page: https://github.com/o2r-project/geoextent
Author: o2r-project
Author-email: o2r.team@uni-muenster.de
License: MIT
Platform: UNKNOWN
Classifier: Programming Language :: Python :: 3
Classifier: License :: OSI Approved :: MIT License
Classifier: Operating System :: OS Independent
Requires-Dist: pyproj
Requires-Dist: geojson (>=2.4.1)
Requires-Dist: pygeoj
Requires-Dist: pyshp
Requires-Dist: pygdal
Requires-Dist: python-dateutil
Requires-Dist: pandas
Requires-Dist: requests
Requires-Dist: numpy
Requires-Dist: traitlets
Requires-Dist: wheel
